cosmiclode/__init__.py
cosmiclode/cosmic_nexus/LICENSE
cosmiclode/cosmic_nexus/README.md
cosmiclode/cosmic_nexus/__init__.py
cosmiclode/cosmic_nexus/cosmic_nexus/__init__.py
cosmiclode/cosmic_nexus/cosmic_nexus/db_connector.py
cosmiclode/cosmic_nexus/cosmic_nexus/db_connector_factory.py
cosmiclode/cosmic_nexus/cosmic_nexus/exceptions.py
cosmiclode/cosmic_nexus/cosmic_nexus/main.py
cosmiclode/cosmic_nexus/cosmic_nexus/mysql_connector.py
cosmiclode/cosmic_nexus/cosmic_nexus/postgresql_connector.py
cosmiclode/cosmic_nexus/cosmic_nexus/sqlserver_connector.py
cosmiclode/cosmic_nexus/pyproject.toml
cosmiclode/cosmic_probe/LICENSE
cosmiclode/cosmic_probe/README.md
cosmiclode/cosmic_probe/__init__.py
cosmiclode/cosmic_probe/cosmic_probe/__init__.py
cosmiclode/cosmic_probe/cosmic_probe/main.py
cosmiclode/cosmic_probe/cosmic_probe/manager.py
cosmiclode/cosmic_probe/cosmic_probe/metadata.py
cosmiclode/cosmic_probe/cosmic_probe/profile.py
cosmiclode/cosmic_probe/pyproject.toml
cosmiclode-0.1.6.dist-info/LICENSE
cosmiclode-0.1.6.dist-info/METADATA
cosmiclode-0.1.6.dist-info/WHEEL
cosmiclode-0.1.6.dist-info/RECORD
